src/__version__.py
src/main.py
src/models/jira_actions.py
src/models/jira_tickets.py
src/tools/jira_executor.py
src/tools/tool_utils.py
jira_tools_mcp-0.2.2.dist-info/METADATA
jira_tools_mcp-0.2.2.dist-info/WHEEL
jira_tools_mcp-0.2.2.dist-info/entry_points.txt
jira_tools_mcp-0.2.2.dist-info/licenses/LICENSE
jira_tools_mcp-0.2.2.dist-info/RECORD
