Metadata-Version: 2.4
Name: jira-tools-mcp
Version: 0.2.2
Summary: Jira MCP for controlling Jira through Jira Command Line.
License-File: LICENSE
Requires-Python: >=3.12
Requires-Dist: mcp[cli]>=1.25.0
Requires-Dist: pydantic>=2.0.0
Requires-Dist: python-dotenv>=1.0.0
Provides-Extra: dev
Requires-Dist: pytest-cov>=4.0.0; extra == 'dev'
Requires-Dist: pytest>=8.0.0; extra == 'dev'
